langgraph_checkpoint_surrealdb/__init__.py
langgraph_checkpoint_surrealdb-2.0.0.dist-info/METADATA
langgraph_checkpoint_surrealdb-2.0.0.dist-info/WHEEL
langgraph_checkpoint_surrealdb-2.0.0.dist-info/licenses/LICENSE
langgraph_checkpoint_surrealdb-2.0.0.dist-info/RECORD
