Metadata-Version: 2.4
Name: langgraph-checkpoint-surrealdb
Version: 2.0.0
Summary: A SurrealDB Checkpointer for Langgraph with both synchronous and asynchronous support.
Author-email: LUIS NOVO <lfnovo@gmail.com>
License-File: LICENSE
Requires-Dist: langchain-core>=1.0.0
Requires-Dist: langgraph>=1.0.0
Requires-Dist: surrealdb>=1.0.3
